asseteour/__init__.py
asseteour/asset_enroller.py
asseteour/asset_populator.py
asseteour/hash_code_helper.py
asseteour/assets/__init__.py
asseteour/assets/traits/__init__.py
asseteour/assets/traits/array_item.py
asseteour/assets/traits/metadata.py
asseteour/assets/traits/values.py
asseteour/assets/traits/vector.py
asseteour/assets/traits/image_traits/__init__.py
asseteour/assets/traits/image_traits/image.py
asseteour/assets/traits/image_traits/mask.py
asseteour/assets/traits/image_traits/mask_segments.py
asseteour/builder/__init__.py
asseteour/builder/asset_builder.py
asseteour/github_app/__init__.py
asseteour/github_app/git_webhook_helper.py
asseteour/github_app/github_helper.py
asseteour/resolver/__init__.py
asseteour/resolver/asset_resolver.py
asseteour/resolver/base_asset_wrapper.py
asseteour/resolver/resolver_parameter.py
asseteour-0.1.29.dist-info/LICENSE
asseteour-0.1.29.dist-info/METADATA
asseteour-0.1.29.dist-info/WHEEL
asseteour-0.1.29.dist-info/top_level.txt
asseteour-0.1.29.dist-info/RECORD
