Metadata-Version: 2.2
Name: asseteour
Version: 0.1.29
Summary: A lite derived configuration system
Home-page: https://github.com/ImagineersHub/asseteour
Author: esunvoteb
Author-email: esun@voteb.com
License: MIT
Keywords: python,configuration,config,derived,json
Classifier: Development Status :: 3 - Alpha
Classifier: Intended Audience :: Developers
Classifier: Topic :: Software Development :: Build Tools
Classifier: License :: OSI Approved :: MIT License
Classifier: Programming Language :: Python :: 3.7
Classifier: Programming Language :: Python :: 3.8
Classifier: Programming Language :: Python :: 3.9
License-File: LICENSE
Requires-Dist: pydantic>=1.7.4
Requires-Dist: matplotlib>=3.5.1
Requires-Dist: PyGithub>=2.1.1
Requires-Dist: compipe>=0.2.3
Dynamic: author
Dynamic: author-email
Dynamic: classifier
Dynamic: description
Dynamic: description-content-type
Dynamic: home-page
Dynamic: keywords
Dynamic: license
Dynamic: requires-dist
Dynamic: summary
